jasmine_eth/__init__.py
jasmine_eth/sdk.py
jasmine_eth/contracts/TFCManager.abi.json
jasmine_eth/contracts/TFCManager.bin
jasmine_eth/contracts/TFCToken.abi.json
jasmine_eth/contracts/TFCToken.bin
tests/__init__.py
tests/test_sdk.py
tests/utils.py
jasmine_eth-0.0.5.dist-info/LICENSE
jasmine_eth-0.0.5.dist-info/METADATA
jasmine_eth-0.0.5.dist-info/WHEEL
jasmine_eth-0.0.5.dist-info/top_level.txt
jasmine_eth-0.0.5.dist-info/RECORD
