Metadata-Version: 2.1
Name: jasmine-eth
Version: 0.0.5
Summary: Jasmine Project Ethereum SDK (Python)
Home-page: https://github.com/Troublor/jasmine-eth-python
Author: Troublor
Author-email: troublor@live.com
License: UNKNOWN
Platform: UNKNOWN
Classifier: Programming Language :: Python :: 3
Classifier: License :: OSI Approved :: Apache Software License
Classifier: Operating System :: OS Independent
Requires-Python: >=3.6
Requires-Dist: web3 (==5.13.1)
